{
  "project_info": {
    "project_number": "363822683587",
    "firebase_url": "https://fir-auth-bed89.firebaseio.com",
    "project_id": "fir-auth-bed89",
    "storage_bucket": "fir-auth-bed89.appspot.com"
  },
  "client": [
    {
      "client_info": {
        "mobilesdk_app_id": "1:363822683587:android:ff6d1f8e1d6562af005976",
        "android_client_info": {
          "package_name": "com.example.firebaseauth"
        }
      },
      "oauth_client": [
        {
          "client_id": "363822683587-mu9sj4dhs9r35h05pt9mj6dn9s4d3p9i.apps.googleusercontent.com",
          "client_type": 3
        }
      ],
      "api_key": [
        {
          "current_key": "AIzaSyAwrzCLktXqeZ5rg3VdrGibB2zcwJMlqng"
        }
      ],
      "services": {
        "appinvite_service": {
          "other_platform_oauth_client": [
            {
              "client_id": "363822683587-mu9sj4dhs9r35h05pt9mj6dn9s4d3p9i.apps.googleusercontent.com",
              "client_type": 3
            }
          ]
        }
      }
    }
  ],
  "configuration_version": "1"
}